{
  "id": 174,
  "locations": [],
  "evolution": [
    "なつき"
  ],
  "level_up_moves": [
    {
      "level": 9,
      "name": "はたく"
    },
    {
      "level": 1,
      "name": "うたう"
    },
    {
      "level": 4,
      "name": "まるくなる"
    },
    {
      "level": 14,
      "name": "てんしのキッス"
    },
    {
      "level": 1,
      "name": "あまえる"
    }
  ],
  "machines": [
    "かえんほうしゃ",
    "ソーラービーム",
    "あなをほる",
    "どくどく",
    "サイコキネシス",
    "かげぶんしん",
    "ひかりのかべ",
    "リフレクター",
    "だいもんじ",
    "ねむる",
    "まもる",
    "メロメロ",
    "おんがえし",
    "やつあたり",
    "しんぴのまもり",
    "めざめるパワー",
    "あまごい",
    "にほんばれ",
    "シャドーボール",
    "からげんき",
    "ひみつのちから",
    "でんげきは",
    "みずのはどう"
  ],
  "hms": [
    "フラッシュ"
  ]
}
