{
  "id": 285,
  "locations": [],
  "evolution": [
    "Lv23"
  ],
  "level_up_moves": [
    {
      "level": 22,
      "name": "ずつき"
    },
    {
      "level": 4,
      "name": "たいあたり"
    },
    {
      "level": 1,
      "name": "すいとる"
    },
    {
      "level": 16,
      "name": "メガドレイン"
    },
    {
      "level": 10,
      "name": "やどりぎのタネ"
    },
    {
      "level": 36,
      "name": "せいちょう"
    },
    {
      "level": 28,
      "name": "どくのこな"
    },
    {
      "level": 7,
      "name": "しびれごな"
    },
    {
      "level": 54,
      "name": "キノコのほうし"
    },
    {
      "level": 45,
      "name": "ギガドレイン"
    }
  ],
  "machines": [
    "ソーラービーム",
    "どくどく",
    "かげぶんしん",
    "ねむる",
    "まもる",
    "ヘドロばくだん",
    "ギガドレイン",
    "メロメロ",
    "おんがえし",
    "やつあたり",
    "しんぴのまもり",
    "めざめるパワー",
    "にほんばれ",
    "からげんき",
    "よこどり",
    "ひみつのちから",
    "タネマシンガン"
  ],
  "hms": [
    "フラッシュ"
  ]
}
