{
  "id": 351,
  "locations": [],
  "evolution": [],
  "level_up_moves": [
    {
      "level": 1,
      "name": "たいあたり"
    },
    {
      "level": 10,
      "name": "ひのこ"
    },
    {
      "level": 10,
      "name": "みずでっぽう"
    },
    {
      "level": 10,
      "name": "こなゆき"
    },
    {
      "level": 20,
      "name": "あまごい"
    },
    {
      "level": 20,
      "name": "にほんばれ"
    },
    {
      "level": 20,
      "name": "あられ"
    },
    {
      "level": 30,
      "name": "ウェザーボール"
    }
  ],
  "machines": [
    "かえんほうしゃ",
    "れいとうビーム",
    "ふぶき",
    "ソーラービーム",
    "１０まんボルト",
    "かみなり",
    "どくどく",
    "かげぶんしん",
    "だいもんじ",
    "ねむる",
    "どろぼう",
    "まもる",
    "すなあらし",
    "メロメロ",
    "おんがえし",
    "やつあたり",
    "めざめるパワー",
    "あまごい",
    "にほんばれ",
    "シャドーボール",
    "あられ",
    "からげんき",
    "ひみつのちから",
    "でんげきは",
    "みずのはどう"
  ],
  "hms": [
    "フラッシュ"
  ]
}
