{
  "id": 197,
  "name": "ブラッキー",
  "types": [
    "あく"
  ],
  "category": "げっこうポケモン",
  "height": "1.0m",
  "weight": "27.0kg",
  "abilities": [
    {
      "n": "シンクロ",
      "d": "自分が　なってしまった　どくや　まひや　やけどを　相手に　うつす。"
    }
  ],
  "evolutions": [
    {
      "id": 133,
      "n": "イーブイ"
    },
    {
      "id": 134,
      "n": "シャワーズ"
    },
    {
      "id": 135,
      "n": "サンダース"
    },
    {
      "id": 136,
      "n": "ブースター"
    },
    {
      "id": 196,
      "n": "エーフィ"
    },
    {
      "id": 197,
      "n": "ブラッキー"
    },
    {
      "id": 470,
      "n": "リーフィア"
    },
    {
      "id": 471,
      "n": "グレイシア"
    },
    {
      "id": 700,
      "n": "ニンフィア"
    }
  ],
  "desc": "月の　光が　イーブイの　遺伝子を　変化させた。　闇に　潜み　獲物を　待つ。　（『Pok&eacute;mon LEGENDS Z-A』より）"
}