{
  "id": 228,
  "name": "デルビル",
  "types": [
    "あく",
    "ほのお"
  ],
  "category": "ダークポケモン",
  "height": "0.6m",
  "weight": "10.8kg",
  "abilities": [
    {
      "n": "はやおき",
      "d": "ねむり状態に　なっても　２倍の　早さで　目覚める　ことが　できる。"
    },
    {
      "n": "もらいび",
      "d": "ほのおタイプの　技を　受けると　炎を　もらい　自分が　出す　ほのおタイプの　技が　強くなる。"
    }
  ],
  "evolutions": [
    {
      "id": 228,
      "n": "デルビル"
    },
    {
      "id": 229,
      "n": "ヘルガー"
    }
  ],
  "desc": "夜明けごろ　あたり一帯に　響きわたる　不気味な　遠ぼえで　自分たちの　縄張りを　アピール。　（『Pok&eacute;mon LEGENDS Z-A』より）"
}