{
  "id": 301,
  "name": "エネコロロ",
  "types": [
    "ノーマル"
  ],
  "category": "おすましポケモン",
  "height": "1.1m",
  "weight": "32.6kg",
  "abilities": [
    {
      "n": "メロメロボディ",
      "d": "自分に　触った　相手を　メロメロに　することが　ある。"
    },
    {
      "n": "ノーマルスキン",
      "d": "どんな　タイプの　技でも　すべて　ノーマルタイプに　なる。　威力が　少し　上がる。"
    }
  ],
  "evolutions": [
    {
      "id": 300,
      "n": "エネコ"
    },
    {
      "id": 301,
      "n": "エネコロロ"
    }
  ],
  "desc": "うつくしい　けなみを　もち　じょせいトレーナーに　だいにんき。　きまった　すみかを　もたない。　（『ポケットモンスター ブリリアントダイヤモンド・シャイニングパール』より）"
}