{
  "id": 579,
  "name": "ランクルス",
  "types": [
    "エスパー"
  ],
  "category": "ぞうふくポケモン",
  "height": "1.0m",
  "weight": "20.1kg",
  "abilities": [
    {
      "n": "ぼうじん",
      "d": "すなあらしの　ダメージを　受けない。　粉や　胞子の　影響も　受けない。"
    },
    {
      "n": "マジックガード",
      "d": "攻撃　以外では　ダメージを　受けない。"
    }
  ],
  "evolutions": [
    {
      "id": 577,
      "n": "ユニラン"
    },
    {
      "id": 578,
      "n": "ダブラン"
    },
    {
      "id": 579,
      "n": "ランクルス"
    }
  ],
  "desc": "発揮した　サイコパワーを　使い　特殊な　液体で　つくられた　腕を　操り　岩を　砕く。　（『ポケットモンスター スカーレット』より）"
}