{
  "id": 829,
  "name": "ヒメンカ",
  "types": [
    "くさ"
  ],
  "category": "はなかざりポケモン",
  "height": "0.4m",
  "weight": "2.2kg",
  "abilities": [
    {
      "n": "わたげ",
      "d": "攻撃を　受けると　わたげを　ばらまいて　自分以外の　ポケモン　すべての　素早さを　下げる。"
    },
    {
      "n": "さいせいりょく",
      "d": "手持ちに　引っ込むと　ＨＰが　少し　回復する。"
    }
  ],
  "evolutions": [
    {
      "id": 829,
      "n": "ヒメンカ"
    },
    {
      "id": 830,
      "n": "ワタシラガ"
    }
  ],
  "desc": "いっぽんあしを　じめんに　さして　ひのひかりを　たっぷり　あびると　はなびらが　あざやかに　いろづく。　（『ポケットモンスター ソード』より）"
}